{
  "tasks": [
    {
      "id": "047de7e5-9914-4262-9822-21799d69905c",
      "taskName": "Do Laundry",
      "dateCreated": "2024-09-05T01:43:25.205Z"
    },
    {
      "id": "1e0c141d-f03f-4526-8dcc-f45be7582713",
      "taskName": "Name cat",
      "dateCreated": "2024-09-05T01:44:50.274Z"
    },
    {
      "id": "a8f4eabc-e247-4339-9e27-2f1d01f48912",
      "taskName": "do interview",
      "dateCreated": "2024-09-12T19:02:52.219Z"
    },
    {
      "id": "ee7005a7-a1ea-41e4-8b1f-8231d0ddf1f9",
      "taskName": "Interview",
      "dateCreated": "2024-09-12T20:05:31.141Z"
    }
  ]
}